scrapy_webdriver/.mypy_cache/.gitignore
scrapy_webdriver/.mypy_cache/3.12/@plugins_snapshot.json
scrapy_webdriver/.mypy_cache/3.12/__future__.data.json
scrapy_webdriver/.mypy_cache/3.12/__future__.meta.json
scrapy_webdriver/.mypy_cache/3.12/_ast.data.json
scrapy_webdriver/.mypy_cache/3.12/_ast.meta.json
scrapy_webdriver/.mypy_cache/3.12/_blake2.data.json
scrapy_webdriver/.mypy_cache/3.12/_blake2.meta.json
scrapy_webdriver/.mypy_cache/3.12/_bz2.data.json
scrapy_webdriver/.mypy_cache/3.12/_bz2.meta.json
scrapy_webdriver/.mypy_cache/3.12/_codecs.data.json
scrapy_webdriver/.mypy_cache/3.12/_codecs.meta.json
scrapy_webdriver/.mypy_cache/3.12/_collections_abc.data.json
scrapy_webdriver/.mypy_cache/3.12/_collections_abc.meta.json
scrapy_webdriver/.mypy_cache/3.12/_compression.data.json
scrapy_webdriver/.mypy_cache/3.12/_compression.meta.json
scrapy_webdriver/.mypy_cache/3.12/_decimal.data.json
scrapy_webdriver/.mypy_cache/3.12/_decimal.meta.json
scrapy_webdriver/.mypy_cache/3.12/_frozen_importlib.data.json
scrapy_webdriver/.mypy_cache/3.12/_frozen_importlib.meta.json
scrapy_webdriver/.mypy_cache/3.12/_frozen_importlib_external.data.json
scrapy_webdriver/.mypy_cache/3.12/_frozen_importlib_external.meta.json
scrapy_webdriver/.mypy_cache/3.12/_hashlib.data.json
scrapy_webdriver/.mypy_cache/3.12/_hashlib.meta.json
scrapy_webdriver/.mypy_cache/3.12/_io.data.json
scrapy_webdriver/.mypy_cache/3.12/_io.meta.json
scrapy_webdriver/.mypy_cache/3.12/_markupbase.data.json
scrapy_webdriver/.mypy_cache/3.12/_markupbase.meta.json
scrapy_webdriver/.mypy_cache/3.12/_multibytecodec.data.json
scrapy_webdriver/.mypy_cache/3.12/_multibytecodec.meta.json
scrapy_webdriver/.mypy_cache/3.12/_queue.data.json
scrapy_webdriver/.mypy_cache/3.12/_queue.meta.json
scrapy_webdriver/.mypy_cache/3.12/_random.data.json
scrapy_webdriver/.mypy_cache/3.12/_random.meta.json
scrapy_webdriver/.mypy_cache/3.12/_sitebuiltins.data.json
scrapy_webdriver/.mypy_cache/3.12/_sitebuiltins.meta.json
scrapy_webdriver-1.0.10.dist-info/LICENSE
scrapy_webdriver-1.0.10.dist-info/METADATA
scrapy_webdriver-1.0.10.dist-info/WHEEL
scrapy_webdriver-1.0.10.dist-info/RECORD
