Metadata-Version: 2.1
Name: scrapy_webdriver
Version: 1.0.10
Summary: Scrapy extension for handle pages with selenium
License: MIT
Author: aleksey
Author-email: kvyatkovsky89@gmail.com
Requires-Python: >=3.10,<4.0
Classifier: License :: OSI Approved :: MIT License
Classifier: Operating System :: OS Independent
Classifier: Programming Language :: Python :: 3
Classifier: Programming Language :: Python :: 3.10
Classifier: Programming Language :: Python :: 3.11
Classifier: Programming Language :: Python :: 3.12
Requires-Dist: beautifulsoup4 (>=4.13.3,<5.0.0)
Requires-Dist: pyvirtualdisplay (>=3.0,<4.0)
Requires-Dist: scrapy (>=2.12.0,<3.0.0)
Requires-Dist: selenium (>=4.29.0,<5.0.0)
Requires-Dist: webdriver-manager (>=4.0.2,<5.0.0)
